tgdl/__init__.py
tgdl/__main__.py
tgdl/auth.py
tgdl/cli.py
tgdl/config.py
tgdl/crypto.py
tgdl/downloader.py
tgdl/list.py
tgdl/utils.py
tgdl-1.1.6.dist-info/licenses/LICENSE
tgdl-1.1.6.dist-info/METADATA
tgdl-1.1.6.dist-info/WHEEL
tgdl-1.1.6.dist-info/entry_points.txt
tgdl-1.1.6.dist-info/top_level.txt
tgdl-1.1.6.dist-info/RECORD
