Metadata-Version: 2.4
Name: tgdl
Version: 1.1.6
Summary: A high-performance CLI tool for downloading media from Telegram
Home-page: https://github.com/kavidu-dilhara/tgdl
Author: kavidu-dilhara
Author-email: kavidu-dilhara <contact@kavidudilhara.eu.org>
License: MIT
Project-URL: Homepage, https://github.com/kavidu-dilhara/tgdl
Project-URL: Documentation, https://github.com/kavidu-dilhara/tgdl#readme
Project-URL: Repository, https://github.com/kavidu-dilhara/tgdl
Project-URL: Bug Tracker, https://github.com/kavidu-dilhara/tgdl/issues
Keywords: telegram,downloader,media,cli,async
Classifier: Development Status :: 5 - Production/Stable
Classifier: Intended Audience :: Developers
Classifier: License :: OSI Approved :: MIT License
Classifier: Programming Language :: Python :: 3
Classifier: Programming Language :: Python :: 3.7
Classifier: Programming Language :: Python :: 3.8
Classifier: Programming Language :: Python :: 3.9
Classifier: Programming Language :: Python :: 3.10
Classifier: Programming Language :: Python :: 3.11
Requires-Python: >=3.7
License-File: LICENSE
Requires-Dist: telethon>=1.42.0
Requires-Dist: click>=8.3.1
Requires-Dist: tqdm>=4.67.1
Requires-Dist: aiofiles>=25.1.0
Requires-Dist: cryptography>=46.0.3
Provides-Extra: dev
Requires-Dist: pytest>=9.0.0; extra == "dev"
Requires-Dist: pytest-asyncio>=1.3.0; extra == "dev"
Requires-Dist: black>=25.11.0; extra == "dev"
Requires-Dist: flake8>=7.3.0; extra == "dev"
Dynamic: author
Dynamic: home-page
Dynamic: license-file
Dynamic: requires-python
